{
	"description": "项目配置文件。",
	"setting": {
		"urlCheck": true,
		"es6": true,
		"postcss": true,
		"minified": true
	},
	"compileType": "weapp",
	"libVersion": "1.6.0",
	"appid": "",
	"projectname": "%E4%BE%BF%E5%88%A9%E6%9F%9C22",
	"condition": {
		"weapp": {
			"current": -1,
			"list": [
				{
					"id": -1,
					"name": "1",
					"pathName": "pages/restaurant/restaurant-single/index",
					"query": ""
				}
			]
		},
		"search": {
			"current": -1,
			"list": []
		},
		"conversation": {
			"current": -1,
			"list": []
		}
	}
}